gmtd/__init__.py
gmtd/cli.py
gmtd-1.1.0b2.dist-info/entry_points.txt
gmtd-1.1.0b2.dist-info/LICENSE
gmtd-1.1.0b2.dist-info/WHEEL
gmtd-1.1.0b2.dist-info/METADATA
gmtd-1.1.0b2.dist-info/RECORD
