Metadata-Version: 2.1
Name: gmtd
Version: 1.1.0b2
Summary: Give Me the Docs finds documentation links for Python packages so you don't have to.
Author-email: Ben Soyka <bensoyka@icloud.com>
Requires-Python: ~=3.8
Classifier: Development Status :: 4 - Beta
Classifier: Environment :: Console
Classifier: Intended Audience :: Developers
Classifier: Natural Language :: English
Classifier: License :: OSI Approved :: MIT License
Classifier: Programming Language :: Python
Classifier: Programming Language :: Python :: 3
Classifier: Programming Language :: Python :: 3.8
Classifier: Programming Language :: Python :: 3.9
Classifier: Programming Language :: Python :: 3.10
Requires-Dist: colorama==0.4.4
Project-URL: Changelog, https://github.com/bsoyka/gmtd/releases
Project-URL: Documentation, https://github.com/bsoyka/gmtd#readme
Project-URL: Source, https://github.com/bsoyka/gmtd
